PCSOLotto/PCSOLotto.py
PCSOLotto/__init__.py
PCSOLotto_Webscraper-0.0.23.dist-info/LICENSE.txt
PCSOLotto_Webscraper-0.0.23.dist-info/METADATA
PCSOLotto_Webscraper-0.0.23.dist-info/WHEEL
PCSOLotto_Webscraper-0.0.23.dist-info/top_level.txt
PCSOLotto_Webscraper-0.0.23.dist-info/RECORD
