Metadata-Version: 2.1
Name: PCSOLotto_Webscraper
Version: 0.0.23
Summary: "CLI & Class library for webscraping lottery results from PCSO website"
Home-page: https://github.com/lonewanderer27/PCSOLotto_Webscraper
Author: Adriane James
Author-email: adrianejames27@gmail.com
Project-URL: Bug Tracker, https://github.com/lonewanderer27/PCSOLotto_Webscraper/issues
Classifier: Programming Language :: Python :: 3
Classifier: License :: OSI Approved :: Apache Software License
Classifier: Operating System :: OS Independent
Requires-Python: >=3.6
License-File: LICENSE.txt
